{
    "type": "origins:active_self",
    "cooldown": 1,
    "condition": {
		"type": "origins:command",
		"command": "data get entity @s SelectedItemSlot",
		"comparison": "==",
		"compare_to": 0
	},
    "entity_action": {
        "type": "origins:execute_command",
        "command": "gamemode spectator @s"
    },
    "key": {
        "key": "key.origins.primary_active",
        "continuous": false
    },
    "hud_render": {
        "should_render": false,
        "sprite_location": "origins:textures/gui/resource_bar.png"
    },
    "name": "Vanish",
    "description": "Vanish out of thin air for up to a minute"
}